brymck/__init__.py
brymck/risk/__init__.py
brymck/risk/v1/__init__.py
brymck/risk/v1/covariance_pb2.py
brymck/risk/v1/covariance_pb2_grpc.py
brymck/risk/v1/frequency_pb2.py
brymck/risk/v1/frequency_pb2_grpc.py
brymck/risk/v1/return_time_series_entry_pb2.py
brymck/risk/v1/return_time_series_entry_pb2_grpc.py
brymck/risk/v1/risk_api_pb2.py
brymck/risk/v1/risk_api_pb2_grpc.py
brymck_risk-0.0.5.dist-info/METADATA
brymck_risk-0.0.5.dist-info/WHEEL
brymck_risk-0.0.5.dist-info/top_level.txt
brymck_risk-0.0.5.dist-info/RECORD
